jrnlsync/__init__.py
jrnlsync/__main__.py
jrnlsync/__version__.py
jrnlsync/cli.py
jrnlsync/config.py
jrnlsync/sync.py
jrnlsync-0.1.11.dist-info/METADATA
jrnlsync-0.1.11.dist-info/WHEEL
jrnlsync-0.1.11.dist-info/entry_points.txt
jrnlsync-0.1.11.dist-info/top_level.txt
jrnlsync-0.1.11.dist-info/RECORD
